ULA.vhd
library ieee;
use ieee.std_logic_1164.all;
use ieee.numeric_std.all; 

entity ULA is
    port
    (
        rg1 : in  unsigned (15 downto 0); --operando A da ULA
        rg2 : in  unsigned (15 downto 0); --operando B da ULA
        sel : in  unsigned  (1 downto 0); --selecao da operacao da ULA
        rg_out : out unsigned (15 downto 0); --resultado da ULA
        Z   : out std_logic; -- flag de zero
        N   : out std_logic; -- flag de negativo
        V   : out std_logic -- flag de overflow
    );
end entity;

architecture ULA of ULA is 

signal result: unsigned(15 downto 0);
signal overflow: std_logic;
begin
 
    result <= rg1+rg2 when sel = "00" else --soma

           rg1-rg2 when sel = "01" else --sub

           rg1 xor rg2 when sel = "10" else -- xor lógico

           rg1 and rg2 when sel = "11" else -- and lógico
           "0000000000000000";

    N <= result(15); -- flag de negativo

    overflow <= '1' when (sel="00" and rg1(15)=rg2(15) and rg1(15) /= result(15)) else         -- overflow
         '1' when (sel="01" and rg1(15)/=rg2(15) and result(15)/=rg1(15)) else
            '0';

    Z <= '1' when result = "0000000000000000" and overflow='0' else -- flag de zero
        '0';

    V <= overflow;
    
    rg_out <= result;

end architecture;

reg16bits.vhd
library ieee;
use ieee.std_logic_1164.all;
use ieee.numeric_std.all;
entity reg16bits is
   port( 
         clk      : in std_logic;
         rst      : in std_logic;
         wr_en    : in std_logic;
         data_in  : in unsigned(15 downto 0);
         data_out : out unsigned(15 downto 0)
   );
end entity;

architecture a_reg16bits of reg16bits is
   signal registro: unsigned(15 downto 0);
begin
   process(clk, rst)
   begin
       if rst = '1' then
           registro <= (others => '0');
       elsif rising_edge(clk) then
           if wr_en = '1' then
               registro <= data_in;
           end if;
       end if;
   end process;
   
   data_out <= registro;  -- conexao direta, fora do processo
end architecture;

decoder3x6.vhd
library ieee;
use ieee.std_logic_1164.all;
use ieee.numeric_std.all;

entity decoder3x6 is
    port(
        sel: in unsigned(4 downto 0);
        s0 : out std_logic;
        s1 : out std_logic;
        s2 : out std_logic;
        s3 : out std_logic;
        s4 : out std_logic;
        s5 : out std_logic
    );
end entity;

architecture a_decoder3x6 of decoder3x6 is
begin
    s0 <= '1' when sel = "00000" else '0';
    s1 <= '1' when sel = "00001" else '0';
    s2 <= '1' when sel = "00010" else '0';
    s3 <= '1' when sel = "00011" else '0';
    s4 <= '1' when sel = "00100" else '0';
    s5 <= '1' when sel = "00101" else '0';
end architecture;

bancoRegs.vhd
library ieee;
use ieee.std_logic_1164.all;
use ieee.numeric_std.all;

entity bancoRegs is
    port( 
        clk      : in std_logic; --clock
        rst      : in std_logic; --reset geral
        wr_en    : in std_logic; -- write enable do banco de regs
        data_wr  : in unsigned(15 downto 0); --dado a escrever no banco de registradores
        reg_wr   : in unsigned(4 downto 0); --registrador a escrever o dado no banco de registradores
        reg_r1   : in unsigned(4 downto 0); --registrador a ler do banco de registradores
        data_r1  : out unsigned(15 downto 0) --dado lido do banco de registradores
   );
end entity;

architecture a_bancoRegs of bancoRegs is
    component reg16bits
    port( 
        clk      : in std_logic;
        rst      : in std_logic;
        wr_en    : in std_logic;
        data_in  : in unsigned(15 downto 0);
        data_out : out unsigned(15 downto 0)
    );
    end component;

    component decoder3x6 
    port(
        sel:in unsigned(4 downto 0);
        s0: out std_logic;
        s1: out std_logic;
        s2: out std_logic;
        s3: out std_logic;
        s4: out std_logic;
        s5: out std_logic
    );
    end component;

    signal out0, out1, out2, out3, out4, out5: unsigned(15 downto 0);
    signal wr_en0, wr_en1, wr_en2, wr_en3, wr_en4, wr_en5: std_logic;

    begin

        data_r1 <=  out0 when reg_r1="00000" else
                    out1 when reg_r1="00001" else
                    out2 when reg_r1="00010" else
                    out3 when reg_r1="00011" else
                    out4 when reg_r1="00100" else
                    out5 when reg_r1="00101" 
                    else "0000000000000000";

        decoder_wr : decoder3x6 
        port map(
            sel=>reg_wr,
            s0=> wr_en0,
            s1=> wr_en1,
            s2=> wr_en2,
            s3=> wr_en3,
            s4=> wr_en4,
            s5=> wr_en5
            );

        rg0: reg16bits
        port map (clk=>clk, rst=>rst, wr_en=>wr_en0, data_in=>data_wr, data_out=>out0);

        rg1: reg16bits
        port map (clk=>clk, rst=>rst, wr_en=>wr_en1, data_in=>data_wr, data_out=>out1);

        rg2: reg16bits
        port map (clk=>clk, rst=>rst, wr_en=>wr_en2, data_in=>data_wr, data_out=>out2);

        rg3: reg16bits
        port map (clk=>clk, rst=>rst, wr_en=>wr_en3, data_in=>data_wr, data_out=>out3);

        rg4: reg16bits
        port map (clk=>clk, rst=>rst, wr_en=>wr_en4, data_in=>data_wr, data_out=>out4);

        rg5: reg16bits
        port map (clk=>clk, rst=>rst, wr_en=>wr_en5, data_in=>data_wr, data_out=>out5);

end architecture;

topLevel.vhd
library ieee;
use ieee.std_logic_1164.all;
use ieee.numeric_std.all;

entity topLevel is
    port(
         clk      : in std_logic;
         rst      : in std_logic;
         wr_en    : in std_logic;
         ula_op   : in unsigned(1 downto 0);
         data_wr  : in unsigned(15 downto 0);
         const    : in unsigned(15 downto 0);
         reg_wr   : in unsigned(4 downto 0);
         reg_r1   : in unsigned(4 downto 0);
         A_wr_sel : in unsigned(1 downto 0); --seleciona fonte do dado a escrever no A
         A_we     : in std_logic;            --habilita escrita no acumulador
         overflow : out std_logic;
         negativo : out std_logic;
         zero     : out std_logic
        );
end entity;

architecture a_topLevel of topLevel is

    component bancoRegs 
        port( 
            clk      : in std_logic;
            rst      : in std_logic;
            wr_en    : in std_logic;
            data_wr  : in unsigned(15 downto 0);
            reg_wr   : in unsigned(4 downto 0);
            reg_r1   : in unsigned(4 downto 0);
            data_r1  : out unsigned(15 downto 0)
            );
    end component;

    component ULA
        port
        (
            rg1 : in  unsigned (15 downto 0); -- usado como A
            rg2 : in  unsigned (15 downto 0); -- possivel cte
            sel : in  unsigned  (1 downto 0);
            rg_out : out unsigned (15 downto 0);
            Z   : out std_logic;
            N   : out std_logic;
            V   : out std_logic
        );
    end component;

    component reg16bits 
        port( 
            clk      : in std_logic;
            rst      : in std_logic;
            wr_en    : in std_logic;
            data_in  : in unsigned(15 downto 0);
            data_out : out unsigned(15 downto 0)
        );
    end component;


    signal result, A_in, A_out, rg1: unsigned(15 downto 0);

    begin

        A: reg16bits
        port map (clk=>clk, rst=>rst, wr_en=>A_we, data_in=>A_in, data_out=>A_out);

        banco: bancoRegs
        port map (
                  clk=>clk, rst=>rst, 
                  wr_en=>wr_en, data_wr=>data_wr,
                  reg_wr=>reg_wr, reg_r1=>reg_r1, 
                  data_r1=>rg1
                 );

        ULA0: ULA
        port map(
                rg1 => A_out,      -- acumulador
                rg2 => rg1,        -- segundo operando banco
                sel => ula_op,
                rg_out => result,
                Z => zero, N => negativo, V => overflow
                );

        A_in <= result when A_wr_sel = "00" else
                const  when A_wr_sel = "01" else
                "0000000000000000";


end architecture;

toplevel_tb.vhd
library ieee;
use ieee.std_logic_1164.all;
use ieee.numeric_std.all;

entity topLevel_tb is
end entity;

architecture sim of topLevel_tb is

    signal clk      : std_logic := '0';
    signal rst      : std_logic := '1';
    signal wr_en    : std_logic := '0';
    signal ula_op   : unsigned(1 downto 0) := (others => '0');
    signal data_wr  : unsigned(15 downto 0) := (others => '0');
    signal const    : unsigned(15 downto 0) := (others => '0');
    signal reg_wr   : unsigned(4 downto 0) := (others => '0');
    signal reg_r1   : unsigned(4 downto 0) := (others => '0');
    signal A_wr_sel : unsigned(1 downto 0) := (others => '0');
    signal A_we     : std_logic := '0';
    signal overflow : std_logic;
    signal negativo : std_logic;
    signal zero     : std_logic;

    constant clk_period : time := 10 ns;

    component topLevel
        port(
            clk      : in std_logic;
            rst      : in std_logic;
            wr_en    : in std_logic;
            ula_op   : in unsigned(1 downto 0);
            data_wr  : in unsigned(15 downto 0);
            const    : in unsigned(15 downto 0);
            reg_wr   : in unsigned(4 downto 0);
            reg_r1   : in unsigned(4 downto 0);
            A_wr_sel : in unsigned(1 downto 0);
            A_we     : in std_logic;
            overflow : out std_logic;
            negativo : out std_logic;
            zero     : out std_logic
        );
    end component;

begin

    -- Instancia o DUT (Device Under Test)
    DUT: topLevel
        port map (
            clk => clk,
            rst => rst,
            wr_en => wr_en,
            ula_op => ula_op,
            data_wr => data_wr,
            const => const,
            reg_wr => reg_wr,
            reg_r1 => reg_r1,
            A_wr_sel => A_wr_sel,
            A_we => A_we,
            overflow => overflow,
            negativo => negativo,
            zero => zero
        );

    -- Geração do clock
    clk_process : process
    begin
        while true loop
            clk <= '0';
            wait for clk_period / 2;
            clk <= '1';
            wait for clk_period / 2;
        end loop;
    end process;

    -- Estímulos de teste
    stim_proc : process
    begin
        -- Reset inicial ativo por 30ns para garantir inicialização correta
        rst <= '1';
        wait for 30 ns;
        rst <= '0';

        wait for clk_period;

        -- Escreve valor 5 no registrador 1
        wr_en    <= '1';
        data_wr  <= to_unsigned(5, 16);
        reg_wr   <= "00001";  -- Reg 1
        wait for clk_period;

        wr_en    <= '0';  -- desativa escrita

        -- Lê do registrador 1
        reg_r1   <= "00001";

        -- Coloca o valor lido no acumulador (A)
        A_wr_sel <= "00";  -- pegar resultado direto (ajuste se necessário)
        ula_op   <= "00";  -- operação soma (ajuste conforme seu ULA)
        A_we     <= '1';   -- ativa escrita no acumulador
        wait for clk_period;
        A_we     <= '0';

        -- Soma acumulador com uma constante (3)
        const    <= to_unsigned(3, 16);
        A_wr_sel <= "00";  -- valor vindo da ULA
        ula_op   <= "00";  -- operação soma
        A_we     <= '1';
        wait for clk_period;
        A_we     <= '0';

        -- Aguarda mais ciclos para observar comportamento
        wait for 100 ns;

        report "Fim da simulação" severity note;
        wait;
    end process;

end architecture;

wave.vcd
$date
  Mon May 19 11:37:42 2025
$end
$version
  GHDL v0
$end
$timescale
  1 fs
$end
$scope module standard $end
$upscope $end
$scope module std_logic_1164 $end
$upscope $end
$scope module numeric_std $end
$upscope $end
$scope module toplevel_tb $end
$var reg 1 ! clk $end
$var reg 1 " rst $end
$var reg 1 # wr_en $end
$var reg 2 $ ula_op[1:0] $end
$var reg 16 % data_wr[15:0] $end
$var reg 16 & const[15:0] $end
$var reg 5 ' reg_wr[4:0] $end
$var reg 5 ( reg_r1[4:0] $end
$var reg 2 ) a_wr_sel[1:0] $end
$var reg 1 * a_we $end
$var reg 1 + overflow $end
$var reg 1 , negativo $end
$var reg 1 - zero $end
$scope module dut $end
$var reg 1 . clk $end
$var reg 1 / rst $end
$var reg 1 0 wr_en $end
$var reg 2 1 ula_op[1:0] $end
$var reg 16 2 data_wr[15:0] $end
$var reg 16 3 const[15:0] $end
$var reg 5 4 reg_wr[4:0] $end
$var reg 5 5 reg_r1[4:0] $end
$var reg 2 6 a_wr_sel[1:0] $end
$var reg 1 7 a_we $end
$var reg 1 8 overflow $end
$var reg 1 9 negativo $end
$var reg 1 : zero $end
$var reg 16 ; result[15:0] $end
$var reg 16 < a_in[15:0] $end
$var reg 16 = a_out[15:0] $end
$var reg 16 > rg1[15:0] $end
$scope module a $end
$var reg 1 ? clk $end
$var reg 1 @ rst $end
$var reg 1 A wr_en $end
$var reg 16 B data_in[15:0] $end
$var reg 16 C data_out[15:0] $end
$var reg 16 D registro[15:0] $end
$upscope $end
$scope module banco $end
$var reg 1 E clk $end
$var reg 1 F rst $end
$var reg 1 G wr_en $end
$var reg 16 H data_wr[15:0] $end
$var reg 5 I reg_wr[4:0] $end
$var reg 5 J reg_r1[4:0] $end
$var reg 16 K data_r1[15:0] $end
$var reg 16 L out0[15:0] $end
$var reg 16 M out1[15:0] $end
$var reg 16 N out2[15:0] $end
$var reg 16 O out3[15:0] $end
$var reg 16 P out4[15:0] $end
$var reg 16 Q out5[15:0] $end
$var reg 1 R wr_en0 $end
$var reg 1 S wr_en1 $end
$var reg 1 T wr_en2 $end
$var reg 1 U wr_en3 $end
$var reg 1 V wr_en4 $end
$var reg 1 W wr_en5 $end
$scope module decoder_wr $end
$var reg 5 X sel[4:0] $end
$var reg 1 Y s0 $end
$var reg 1 Z s1 $end
$var reg 1 [ s2 $end
$var reg 1 \ s3 $end
$var reg 1 ] s4 $end
$var reg 1 ^ s5 $end
$upscope $end
$scope module rg0 $end
$var reg 1 _ clk $end
$var reg 1 ` rst $end
$var reg 1 a wr_en $end
$var reg 16 b data_in[15:0] $end
$var reg 16 c data_out[15:0] $end
$var reg 16 d registro[15:0] $end
$upscope $end
$scope module rg1 $end
$var reg 1 e clk $end
$var reg 1 f rst $end
$var reg 1 g wr_en $end
$var reg 16 h data_in[15:0] $end
$var reg 16 i data_out[15:0] $end
$var reg 16 j registro[15:0] $end
$upscope $end
$scope module rg2 $end
$var reg 1 k clk $end
$var reg 1 l rst $end
$var reg 1 m wr_en $end
$var reg 16 n data_in[15:0] $end
$var reg 16 o data_out[15:0] $end
$var reg 16 p registro[15:0] $end
$upscope $end
$scope module rg3 $end
$var reg 1 q clk $end
$var reg 1 r rst $end
$var reg 1 s wr_en $end
$var reg 16 t data_in[15:0] $end
$var reg 16 u data_out[15:0] $end
$var reg 16 v registro[15:0] $end
$upscope $end
$scope module rg4 $end
$var reg 1 w clk $end
$var reg 1 x rst $end
$var reg 1 y wr_en $end
$var reg 16 z data_in[15:0] $end
$var reg 16 { data_out[15:0] $end
$var reg 16 | registro[15:0] $end
$upscope $end
$scope module rg5 $end
$var reg 1 } clk $end
$var reg 1 !" rst $end
$var reg 1 "" wr_en $end
$var reg 16 #" data_in[15:0] $end
$var reg 16 $" data_out[15:0] $end
$var reg 16 %" registro[15:0] $end
$upscope $end
$upscope $end
$scope module ula0 $end
$var reg 16 &" rg1[15:0] $end
$var reg 16 '" rg2[15:0] $end
$var reg 2 (" sel[1:0] $end
$var reg 16 )" rg_out[15:0] $end
$var reg 1 *" z $end
$var reg 1 +" n $end
$var reg 1 ," v $end
$var reg 16 -" result[15:0] $end
$var reg 1 ." overflow $end
$upscope $end
$upscope $end
$upscope $end
$enddefinitions $end
#0
0!
1"
0#
b00 $
b0000000000000000 %
b0000000000000000 &
b00000 '
b00000 (
b00 )
0*
0+
0,
1-
0.
1/
00
b00 1
b0000000000000000 2
b0000000000000000 3
b00000 4
b00000 5
b00 6
07
08
09
1:
b0000000000000000 ;
b0000000000000000 <
b0000000000000000 =
b0000000000000000 >
0?
1@
0A
b0000000000000000 B
b0000000000000000 C
b0000000000000000 D
0E
1F
0G
b0000000000000000 H
b00000 I
b00000 J
b0000000000000000 K
b0000000000000000 L
b0000000000000000 M
b0000000000000000 N
b0000000000000000 O
b0000000000000000 P
b0000000000000000 Q
1R
0S
0T
0U
0V
0W
b00000 X
1Y
0Z
0[
0\
0]
0^
0_
1`
1a
b0000000000000000 b
b0000000000000000 c
b0000000000000000 d
0e
1f
0g
b0000000000000000 h
b0000000000000000 i
b0000000000000000 j
0k
1l
0m
b0000000000000000 n
b0000000000000000 o
b0000000000000000 p
0q
1r
0s
b0000000000000000 t
b0000000000000000 u
b0000000000000000 v
0w
1x
0y
b0000000000000000 z
b0000000000000000 {
b0000000000000000 |
0}
1!"
0""
b0000000000000000 #"
b0000000000000000 $"
b0000000000000000 %"
b0000000000000000 &"
b0000000000000000 '"
b00 ("
b0000000000000000 )"
1*"
0+"
0,"
b0000000000000000 -"
0."
#5000000
1!
1.
1?
1E
1_
1e
1k
1q
1w
1}
#10000000
0!
0.
0?
0E
0_
0e
0k
0q
0w
0}
#15000000
1!
1.
1?
1E
1_
1e
1k
1q
1w
1}
#20000000
0!
0.
0?
0E
0_
0e
0k
0q
0w
0}
#25000000
1!
1.
1?
1E
1_
1e
1k
1q
1w
1}
#30000000
0!
0"
0.
0/
0?
0@
0E
0F
0_
0`
0e
0f
0k
0l
0q
0r
0w
0x
0}
0!"
#35000000
1!
1.
1?
1E
1_
1e
1k
1q
1w
1}
#40000000
0!
1#
b0000000000000101 %
b00001 '
0.
10
b0000000000000101 2
b00001 4
0?
0E
1G
b0000000000000101 H
b00001 I
0R
1S
b00001 X
0Y
1Z
0_
0a
b0000000000000101 b
0e
1g
b0000000000000101 h
0k
b0000000000000101 n
0q
b0000000000000101 t
0w
b0000000000000101 z
0}
b0000000000000101 #"
#45000000
1!
1.
1?
1E
b0000000000000101 M
1_
1e
b0000000000000101 i
b0000000000000101 j
1k
1q
1w
1}
#50000000
0!
0#
b00001 (
1*
0-
0.
00
b00001 5
17
0:
b0000000000000101 ;
b0000000000000101 <
b0000000000000101 >
0?
1A
b0000000000000101 B
0E
0G
b00001 J
b0000000000000101 K
0_
0e
0k
0q
0w
0}
b0000000000000101 '"
b0000000000000101 )"
0*"
b0000000000000101 -"
#55000000
1!
1.
b0000000000001010 ;
b0000000000001010 <
b0000000000000101 =
1?
b0000000000001010 B
b0000000000000101 C
b0000000000000101 D
1E
1_
1e
1k
1q
1w
1}
b0000000000000101 &"
b0000000000001010 )"
b0000000000001010 -"
#60000000
0!
b0000000000000011 &
0.
b0000000000000011 3
0?
0E
0_
0e
0k
0q
0w
0}
#65000000
1!
1.
b0000000000001111 ;
b0000000000001111 <
b0000000000001010 =
1?
b0000000000001111 B
b0000000000001010 C
b0000000000001010 D
1E
1_
1e
1k
1q
1w
1}
b0000000000001010 &"
b0000000000001111 )"
b0000000000001111 -"
#70000000
0!
0*
0.
07
0?
0A
0E
0_
0e
0k
0q
0w
0}
